pop_release/conf.py
pop_release/scripts.py
pop_release/version.py
pop_release/acct/twine/default.py
pop_release/acct/twine/settings.py
pop_release/exec/twine/command.py
pop_release/exec/twine/init.py
pop_release/exec/twine/repository.py
pop_release/exec/twine/settings.py
pop_release/exec/twine/contracts/init.py
pop_release/pop_release/cli.py
pop_release/pop_release/dist.py
pop_release/pop_release/gitpy.py
pop_release/pop_release/init.py
pop_release/pop_release/settings.py
pop_release/pop_release/sv.py
pop_release/pop_release/test.py
pop_release/pop_release/twine.py
pop_release/pop_release/version.py
pop_release-15.0.0.dist-info/LICENSE
pop_release-15.0.0.dist-info/METADATA
pop_release-15.0.0.dist-info/WHEEL
pop_release-15.0.0.dist-info/entry_points.txt
pop_release-15.0.0.dist-info/top_level.txt
pop_release-15.0.0.dist-info/RECORD
