Metadata-Version: 2.1
Name: pop-release
Version: 15.0.0
Home-page: https://gitlab.com/saltstack/pop/pop-release
Maintainer: Tyler Johnson
Maintainer-email: tyjohnson@vmware.com
Classifier: Operating System :: OS Independent
Classifier: Programming Language :: Python
Classifier: Programming Language :: Python :: 3.8
Classifier: Programming Language :: Python :: 3.9
Classifier: Programming Language :: Python :: 3.10
Classifier: Programming Language :: Python :: 3.11
Classifier: Development Status :: 5 - Production/Stable
Requires-Python: >=3.8
License-File: LICENSE
Requires-Dist: idem >=23.0.0
Requires-Dist: pop <28.0.0,>=17.0.0
Requires-Dist: pop-config !=12.0.2,!=12.0.3
Requires-Dist: twine ==3.8.0
Requires-Dist: readme-renderer <42.0
Provides-Extra: full
Requires-Dist: gitdb >=1.7.0 ; extra == 'full'
Requires-Dist: semantic-version ; extra == 'full'
Requires-Dist: pytest ; extra == 'full'
Requires-Dist: GitPython ; extra == 'full'
Provides-Extra: git
Requires-Dist: gitdb >=1.7.0 ; extra == 'git'
Requires-Dist: GitPython ; extra == 'git'
Provides-Extra: pytest
Requires-Dist: pytest ; extra == 'pytest'
Provides-Extra: version
Requires-Dist: semantic-version ; extra == 'version'
